experiments/data/download_data.py
experiments/data/download_results.py
experiments/data/subsampling/subsample_f1.py
experiments/data/subsampling/subsample_walmart.py
experiments/evaluation/benchmark.py
experiments/evaluation/benchmark_single_table.py
experiments/evaluation/utility.py
experiments/evaluation/visualize_results.py
experiments/evaluation/gnn_utility/gnn_datasets.py
experiments/evaluation/gnn_utility/model.py
experiments/evaluation/gnn_utility/run_baseline.py
experiments/evaluation/gnn_utility/run_gnn.py
experiments/evaluation/gnn_utility/run_lightgbm.py
experiments/evaluation/gnn_utility/run_utility_benchmark.py
experiments/evaluation/gnn_utility/text_embedder.py
experiments/figures/figure1.py
experiments/figures/figure2.py
experiments/figures/figure3.py
experiments/figures/figure4.py
experiments/figures/figure5.py
experiments/figures/figure6.py
experiments/figures/figure7.py
experiments/generation/clavaddpm/postprocess_dataset.py
experiments/generation/clavaddpm/prepare_dataset.py
experiments/generation/gretel/generate_gretel.py
experiments/generation/mostlyai/generate_mostlyai.py
experiments/generation/rctgan/convert_metadata_to_v0.py
experiments/generation/rctgan/generate_rctgan.py
experiments/generation/rctgan/RCTGAN/setup.py
experiments/generation/rctgan/RCTGAN/tasks.py
experiments/generation/rctgan/RCTGAN/rctgan/__init__.py
experiments/generation/rctgan/RCTGAN/rctgan/demo.py
experiments/generation/rctgan/RCTGAN/rctgan/errors.py
experiments/generation/rctgan/RCTGAN/rctgan/evaluation.py
experiments/generation/rctgan/RCTGAN/rctgan/rctgan.py
experiments/generation/rctgan/RCTGAN/rctgan/utils.py
experiments/generation/rctgan/RCTGAN/rctgan/constraints/__init__.py
experiments/generation/rctgan/RCTGAN/rctgan/constraints/base.py
experiments/generation/rctgan/RCTGAN/rctgan/constraints/errors.py
experiments/generation/rctgan/RCTGAN/rctgan/constraints/tabular.py
experiments/generation/rctgan/RCTGAN/rctgan/constraints/utils.py
syntherela-0.0.4.dist-info/LICENSE
syntherela-0.0.4.dist-info/METADATA
syntherela-0.0.4.dist-info/WHEEL
syntherela-0.0.4.dist-info/top_level.txt
syntherela-0.0.4.dist-info/RECORD
