Metadata-Version: 2.2
Name: syntherela
Version: 0.0.4
Summary: SyntheRela - Synthetic Relational Data Generation Benchmark
Author-email: Martin Jurkovic <martin.jurkovic19@gmail.com>, Valter Hudovernik <valter.hudovernik@gmail.com>
Project-URL: Homepage, https://github.com/martinjurkovic/syntherela
Project-URL: Issues, https://github.com/martinjurkovic/syntherela/issues
Keywords: python,syntherela,synthetic data,relational data,evaluation,benchmark
Classifier: Programming Language :: Python :: 3.8
Classifier: Programming Language :: Python :: 3.9
Classifier: Programming Language :: Python :: 3.10
Classifier: Programming Language :: Python :: 3.11
Classifier: Programming Language :: Python :: 3.12
Classifier: Programming Language :: Python :: 3.13
Classifier: License :: OSI Approved :: MIT License
Classifier: Operating System :: OS Independent
Classifier: Development Status :: 3 - Alpha
Classifier: Topic :: Scientific/Engineering
Classifier: Topic :: Scientific/Engineering :: Artificial Intelligence
Classifier: Intended Audience :: Science/Research
Classifier: Intended Audience :: Education
Classifier: Intended Audience :: Financial and Insurance Industry
Classifier: Intended Audience :: Healthcare Industry
Requires-Python: >=3.8
License-File: LICENSE
Requires-Dist: sdv<2,>=1.9.0
Requires-Dist: seaborn==0.13.2
Requires-Dist: xgboost==1.7.6
Requires-Dist: scikit-learn==1.3.1
Provides-Extra: gnn-utility
Requires-Dist: relbench[example,full]; extra == "gnn-utility"
Requires-Dist: torch_geometric; extra == "gnn-utility"
Requires-Dist: shap; extra == "gnn-utility"
Requires-Dist: tqdm; extra == "gnn-utility"
Requires-Dist: lightgbm; extra == "gnn-utility"
